looking_glass/__init__.py
looking_glass/application.py
looking_glass/looking_glass.db
looking_glass/requirements.txt
looking_glass/lib/__init__.py
looking_glass/lib/__init__.pyc
looking_glass/lib/arp.py
looking_glass/lib/arp.pyc
looking_glass/lib/data_graph.py
looking_glass/lib/data_graph.pyc
looking_glass/lib/data_graph.py~
looking_glass/lib/netflow.py
looking_glass/lib/tables.py
looking_glass/lib/tables.pyc
looking_glass/lib/tables.py~
looking_glass/lib/__pycache__/__init__.cpython-36.pyc
looking_glass/lib/__pycache__/arp.cpython-36.pyc
looking_glass/lib/__pycache__/data_graph.cpython-36.pyc
looking_glass/lib/__pycache__/tables.cpython-36.pyc
looking_glass/static/graph.js
looking_glass/static/graph.js~
looking_glass/static/css/graph.css
looking_glass/static/css/graph.css~
looking_glass/static/css/login.css
looking_glass/static/css/main.css
looking_glass/static/css/main.css~
looking_glass/static/images/beacon-icon.ico
looking_glass/static/images/generic-host.png
looking_glass/static/images/hacker-icon.ico
looking_glass/static/images/linux-icon.png
looking_glass/static/images/redirector-icon.png
looking_glass/static/images/staging-server-icon.png
looking_glass/static/images/windows-icon.png
looking_glass/static/js/vis-4.21.0/.babelrc
looking_glass/static/js/vis-4.21.0/.codeclimate.yml
looking_glass/static/js/vis-4.21.0/.csslintrc
looking_glass/static/js/vis-4.21.0/.eslintrc
looking_glass/static/js/vis-4.21.0/.gitignore
looking_glass/static/js/vis-4.21.0/.mdlrc
looking_glass/static/js/vis-4.21.0/.npmignore
looking_glass/static/js/vis-4.21.0/.travis.yml
looking_glass/static/js/vis-4.21.0/CONTRIBUTING.md
looking_glass/static/js/vis-4.21.0/HISTORY.md
looking_glass/static/js/vis-4.21.0/LICENSE-APACHE-2.0
looking_glass/static/js/vis-4.21.0/LICENSE-MIT
looking_glass/static/js/vis-4.21.0/README.md
looking_glass/static/js/vis-4.21.0/bower.json
looking_glass/static/js/vis-4.21.0/gulpfile.js
looking_glass/static/js/vis-4.21.0/index-graph3d.js
looking_glass-1.0.4.dist-info/LICENSE
looking_glass-1.0.4.dist-info/METADATA
looking_glass-1.0.4.dist-info/WHEEL
looking_glass-1.0.4.dist-info/top_level.txt
looking_glass-1.0.4.dist-info/RECORD
