Metadata-Version: 2.1
Name: looking-glass
Version: 1.0.4
Summary: Web-based tool for visualizing data from network scanning and reconnaissance tools
Home-page: https://github.com/unheardof/LookingGlass
Author: Timothy Heard
License: UNKNOWN
Platform: UNKNOWN
Classifier: Programming Language :: Python :: 3
Classifier: License :: OSI Approved :: Apache Software License
Classifier: Operating System :: OS Independent
Classifier: Environment :: Console
